unplash_python-1.0.0.dist-info/licenses/LICENSE
unsplash/__init__.py
unsplash/client.py
unsplash/endpoints.py
unsplash/exceptions.py
unsplash/models.py
unsplash/utils.py
unplash_python-1.0.0.dist-info/METADATA
unplash_python-1.0.0.dist-info/WHEEL
unplash_python-1.0.0.dist-info/top_level.txt
unplash_python-1.0.0.dist-info/RECORD
